zenframe/__init__.py
zenframe/__main__.py
zenframe/actions.py
zenframe/animate.py
zenframe/argparse.py
zenframe/client.py
zenframe/communicator.py
zenframe/configuration.py
zenframe/console.py
zenframe/finisher.py
zenframe/inotifier.py
zenframe/listener.py
zenframe/mainwindow.py
zenframe/retransler.py
zenframe/screen_saver.py
zenframe/settings.py
zenframe/starter.py
zenframe/text_editor.py
zenframe/unbound.py
zenframe/util.py
zenframe-1.2.0.dist-info/METADATA
zenframe-1.2.0.dist-info/WHEEL
zenframe-1.2.0.dist-info/entry_points.txt
zenframe-1.2.0.dist-info/top_level.txt
zenframe-1.2.0.dist-info/RECORD
