Metadata-Version: 2.1
Name: zenframe
Version: 1.2.0
Summary: Sandbox for computationally-graphical scripts
Home-page: https://github.com/mirmik/zenframe
Author: mirmik
Author-email: netricks@protonmail.com
License: MIT
Keywords: sandbox
Platform: UNKNOWN
Requires-Dist: PyQt5 (!=5.14.1)
Requires-Dist: evalcache
Requires-Dist: psutil
